odoo/addons/bank_statement_foreign_currency/README.rst
odoo/addons/bank_statement_foreign_currency/__init__.py
odoo/addons/bank_statement_foreign_currency/__manifest__.py
odoo/addons/bank_statement_foreign_currency/i18n/bank_statement_foreign_currency.pot
odoo/addons/bank_statement_foreign_currency/static/description/icon.png
odoo/addons/bank_statement_foreign_currency/views/account_view.xml
odoo11_addon_bank_statement_foreign_currency-11.0.1.0.0.99.dev2.dist-info/DESCRIPTION.rst
odoo11_addon_bank_statement_foreign_currency-11.0.1.0.0.99.dev2.dist-info/METADATA
odoo11_addon_bank_statement_foreign_currency-11.0.1.0.0.99.dev2.dist-info/RECORD
odoo11_addon_bank_statement_foreign_currency-11.0.1.0.0.99.dev2.dist-info/WHEEL
odoo11_addon_bank_statement_foreign_currency-11.0.1.0.0.99.dev2.dist-info/metadata.json
odoo11_addon_bank_statement_foreign_currency-11.0.1.0.0.99.dev2.dist-info/top_level.txt
